disguise/__init__.py
disguise/apps.py
disguise/checks.py
disguise/conf.py
disguise/const.py
disguise/forms.py
disguise/locale/django.pot
disguise/locale/ru/LC_MESSAGES/django.mo
disguise/locale/ru/LC_MESSAGES/django.po
disguise/middleware.py
disguise/models.py
disguise/signals.py
disguise/templates/disguise/form.html
disguise/templates/disguise/widget_base.html
disguise/templatetags/__init__.py
disguise/templatetags/disguise_tags.py
disguise/urls.py
disguise/utils.py
disguise/views.py
django_disguise-1.2.0.dist-info/LICENSE
django_disguise-1.2.0.dist-info/WHEEL
django_disguise-1.2.0.dist-info/METADATA
django_disguise-1.2.0.dist-info/RECORD
